{
  "$schema": "https://developer.microsoft.com/json-schemas/fabric/item/report/definition/visualContainer/2.6.0/schema.json",
  "name": "86d35750c9855acb6467",
  "position": {
    "x": 978,
    "y": 380.68309811466804,
    "z": 25000,
    "height": 35.455778745973987,
    "width": 39.1879659823923,
    "tabOrder": 22000
  },
  "visual": {
    "visualType": "actionButton",
    "objects": {
      "icon": [
        {
          "properties": {
            "shapeType": {
              "expr": {
                "Literal": {
                  "Value": "'custom'"
                }
              }
            },
            "image": {
              "image": {
                "name": {
                  "expr": {
                    "Literal": {
                      "Value": "'delete.png'"
                    }
                  }
                },
                "url": {
                  "expr": {
                    "ResourcePackageItem": {
                      "PackageName": "RegisteredResources",
                      "PackageType": 1,
                      "ItemName": "delete9338419624358174.png"
                    }
                  }
                },
                "scaling": {
                  "expr": {
                    "Literal": {
                      "Value": "'Normal'"
                    }
                  }
                }
              }
            }
          },
          "selector": {
            "id": "default"
          }
        },
        {
          "properties": {
            "image": {
              "image": {
                "name": {
                  "expr": {
                    "Literal": {
                      "Value": "'delete (1).png'"
                    }
                  }
                },
                "url": {
                  "expr": {
                    "ResourcePackageItem": {
                      "PackageName": "RegisteredResources",
                      "PackageType": 1,
                      "ItemName": "delete_(1)6572963938964739.png"
                    }
                  }
                },
                "scaling": {
                  "expr": {
                    "Literal": {
                      "Value": "'Normal'"
                    }
                  }
                }
              }
            }
          },
          "selector": {
            "id": "selected"
          }
        },
        {
          "properties": {
            "image": {
              "image": {
                "name": {
                  "expr": {
                    "Literal": {
                      "Value": "'delete (1).png'"
                    }
                  }
                },
                "url": {
                  "expr": {
                    "ResourcePackageItem": {
                      "PackageName": "RegisteredResources",
                      "PackageType": 1,
                      "ItemName": "delete_(1)6928997418808146.png"
                    }
                  }
                },
                "scaling": {
                  "expr": {
                    "Literal": {
                      "Value": "'Normal'"
                    }
                  }
                }
              }
            }
          },
          "selector": {
            "id": "hover"
          }
        }
      ]
    },
    "visualContainerObjects": {
      "title": [
        {
          "properties": {
            "text": {
              "expr": {
                "Literal": {
                  "Value": "'ClosedCloseButton'"
                }
              }
            }
          }
        }
      ],
      "visualLink": [
        {
          "properties": {
            "show": {
              "expr": {
                "Literal": {
                  "Value": "true"
                }
              }
            },
            "type": {
              "expr": {
                "Literal": {
                  "Value": "'Bookmark'"
                }
              }
            },
            "bookmark": {
              "expr": {
                "Literal": {
                  "Value": "'1b2aa3f49bd91e0f0c36'"
                }
              }
            }
          }
        }
      ]
    },
    "drillFilterOtherVisuals": true
  },
  "isHidden": true,
  "howCreated": "InsertVisualButton"
}